fpack/__init__.py
fpack/fields.py
fpack/msg.py
fpack/utils.py
fpack-1.0.3.dist-info/LICENSE
fpack-1.0.3.dist-info/WHEEL
fpack-1.0.3.dist-info/METADATA
fpack-1.0.3.dist-info/RECORD
